MANIFEST.in
README.rst
pyproject.toml
setup.cfg
setup.py
requirements/requirements.txt
t_vault/__init__.py
t_vault/t_vault.py
t_vault/models/__init__.py
t_vault/models/bitwarden/__init__.py
t_vault/models/bitwarden/attachment.py
t_vault/models/bitwarden/bitwarden_item.py
t_vault/models/bitwarden/vault_item.py
t_vault/models/bitwarden/exceptions/__init__.py
t_vault/models/bitwarden/exceptions/bitwarden_download_error.py
t_vault/models/bitwarden/exceptions/bitwarden_install_error.py
t_vault/models/bitwarden/exceptions/bitwarden_not_installed.py
t_vault/models/bitwarden/exceptions/invalid_totp_error.py
t_vault/models/bitwarden/exceptions/unsupported_platform.py
t_vault/models/bitwarden/exceptions/update_custom_fields.py
t_vault/models/bitwarden/exceptions/update_password_error.py
t_vault/models/bitwarden/exceptions/vault_attachement_not_found_error.py
t_vault/models/bitwarden/exceptions/vault_error.py
t_vault/models/bitwarden/exceptions/vault_item_error.py
t_vault/models/bitwarden/exceptions/vault_item_not_found_error.py
t_vault/models/keeper/__init__.py
t_vault/models/keeper/keeper_credentials.py
t_vault/services/__init__.py
t_vault/services/bitwarden/__init__.py
t_vault/services/bitwarden/bitwarden.py
t_vault/services/keeper/__init__.py
t_vault/services/keeper/keeper.py
t_vault/services/keeper/core/__init__.py
t_vault/services/keeper/core/types.py
t_vault/utils/__init__.py
t_vault/utils/core/__init__.py
t_vault/utils/core/bw_port.py
t_vault/utils/core/download_bitwarden.py
t_vault/utils/core/singleton.py
t_vault/utils/services/__init__.py
t_vault/utils/services/logger.py
t_vault_manager.egg-info/PKG-INFO
t_vault_manager.egg-info/SOURCES.txt
t_vault_manager.egg-info/dependency_links.txt
t_vault_manager.egg-info/not-zip-safe
t_vault_manager.egg-info/requires.txt
t_vault_manager.egg-info/top_level.txt
tests/test_t_bitwarden.py
tests/test_t_vault.py