Metadata-Version: 2.4
Name: t_vault_manager
Version: 1.0.3
Summary: Package for seamless interaction with the Bitwarden.
Home-page: https://www.thoughtful.ai/
Author: Thoughtful
Author-email: support@thoughtful.ai
Keywords: t_vault
Classifier: Intended Audience :: Developers
Classifier: Natural Language :: English
Classifier: Programming Language :: Python :: 3
Classifier: Programming Language :: Python :: 3.9
Requires-Python: >=3.9
Requires-Dist: requests>=2.31.0
Requires-Dist: retry>=0.9.2
Requires-Dist: t-object>=0.1.0
Requires-Dist: pyotp>=2.6.0
Requires-Dist: pydantic>=2.11.5
Requires-Dist: keepercommander~=17.0.19
Dynamic: author
Dynamic: author-email
Dynamic: classifier
Dynamic: description
Dynamic: home-page
Dynamic: keywords
Dynamic: requires-dist
Dynamic: requires-python
Dynamic: summary
